precision_greenhouse_fsm.v
// precision_greenhouse_fsm.v
module precision_greenhouse_fsm (
    input  wire clk,
    input  wire reset_n,
    input  wire [5:0] S,       
    output reg  [5:0] A,
    
    // --- NAMA GRAFIK SESUAI REQUEST (SS0_IDLE, SS1_NUTRI...) ---
    output wire SS0_IDLE,
    output wire SS1_NUTRI,
    output wire SS2_WATER,
    output wire SS3_TEMP,
    output wire SS4_SPRAY,
    output wire SS5_FLUSH,
    output wire SS6_GAS,
    output wire SS7_CHAOS
);

    // Parameter Internal (Ganti nama dikit biar ga bentrok sama output)
    parameter ST_IDLE      = 3'b000;
    parameter ST_NUTRI     = 3'b001;
    parameter ST_WATER     = 3'b010;
    parameter ST_TEMP      = 3'b011;
    parameter ST_SPRAY     = 3'b100;
    parameter ST_FLUSH     = 3'b101;
    parameter ST_GAS       = 3'b110;
    parameter ST_CHAOS     = 3'b111;

    reg [2:0] current_state;
    reg [2:0] next_state;

    // --- LOGIKA VISUALISASI ---
    // IDLE & CHAOS = Linear 0 (Mati Terus)
    assign SS0_IDLE    = 1'b0; 
    assign SS7_CHAOS   = 1'b0; 

    // SISANYA MENGIKUTI SENSOR (Bisa Overlap)
    assign SS1_NUTRI   = S[0]; 
    assign SS2_WATER   = S[1]; 
    assign SS3_TEMP    = S[2]; 
    assign SS4_SPRAY   = S[3];
    assign SS5_FLUSH   = S[4];
    assign SS6_GAS     = S[5];

    // Update State
    always @(posedge clk or negedge reset_n) begin
        if (!reset_n) current_state <= ST_IDLE;
        else          current_state <= next_state;
    end

    // Next State Logic
    always @(*) begin
        next_state = current_state;
        if (S[5] == 1'b1)        next_state = ST_GAS;   
        else if (S[4] == 1'b1)   next_state = ST_FLUSH;
        else if (S[3] == 1'b1)   next_state = ST_SPRAY;
        else if (S[2] == 1'b1)   next_state = ST_TEMP;
        else if (S[1] == 1'b1)   next_state = ST_WATER;
        else if (S[0] == 1'b1)   next_state = ST_NUTRI;
        else                     next_state = ST_IDLE;
        
        if (current_state == ST_GAS && S[5] == 0) next_state = ST_IDLE;
    end

    // Output Aktuator
    always @(current_state) begin
        case (current_state)
            ST_NUTRI: A = 6'b000001;
            ST_WATER: A = 6'b000010;
            ST_TEMP:  A = 6'b000100;
            ST_SPRAY: A = 6'b001000;
            ST_FLUSH: A = 6'b010000;
            ST_GAS:   A = 6'b100000;
            default:  A = 6'b000000;
        endcase
    end
endmodule

tb_precision_greenhouse.v
// tb_precision_greenhouse_fsm.v
module tb_precision_greenhouse_fsm;

    reg clk;
    reg reset_n;
    reg [5:0] S_in;
    wire [5:0] A_out;

    // Kabel Visual Baru
    wire SS0_IDLE;
    wire SS1_NUTRI;
    wire SS2_WATER;
    wire SS3_TEMP;
    wire SS4_SPRAY;
    wire SS5_FLUSH;
    wire SS6_GAS;
    wire SS7_CHAOS;

    precision_greenhouse_fsm DUT (
        .clk(clk),
        .reset_n(reset_n),
        .S(S_in),
        .A(A_out),
        .SS0_IDLE(SS0_IDLE),
        .SS1_NUTRI(SS1_NUTRI),
        .SS2_WATER(SS2_WATER),
        .SS3_TEMP(SS3_TEMP),
        .SS4_SPRAY(SS4_SPRAY),
        .SS5_FLUSH(SS5_FLUSH),
        .SS6_GAS(SS6_GAS),
        .SS7_CHAOS(SS7_CHAOS)
    );

    parameter PERIOD = 20;
    initial begin
        clk = 1'b0;
        forever #(PERIOD/2) clk = ~clk;
    end

    initial begin
        $dumpfile("simulasi_greenhouse.vcd");
        $dumpvars(0, tb_precision_greenhouse_fsm);

        // Reset
        reset_n = 1'b0; S_in = 6'b000000; #40;
        reset_n = 1'b1; #40;

        // --- SKENARIO MENYEBAR (SCATTERED) ---
        
        // 1. Mulai dengan Water sebentar
        S_in = 6'b000010; #100; 

        // 2. Tiba-tiba Suhu Panas (Water masih nyala -> Overlap)
        S_in = 6'b000110; #120;

        // 3. Water mati, ganti Spray (Overlap Temp + Spray)
        S_in = 6'b001100; #100;

        // 4. Jeda sebentar
        S_in = 6'b000000; #40;

        // 5. Nutrisi Masuk (Sendirian)
        S_in = 6'b000001; #80;

        // 6. Tiba-tiba butuh Flush
        S_in = 6'b010000; #100;

        // 7. Balik lagi ke Water (Menyebar kan?)
        S_in = 6'b000010; #120;

        // 8. Water + Nutri (Fertigasi)
        S_in = 6'b000011; #150;

        // 9. Jeda
        S_in = 6'b000000; #40;

        // 10. Gas Bocor (Panjang)
        S_in = 6'b100000; #200;

        // 11. Balik lagi ke Suhu Panas (Temp)
        S_in = 6'b000100; #100;

        // 12. Nutrisi lagi (Menyebar di akhir)
        S_in = 6'b000001; #80;

        // Selesai
        S_in = 6'b000000; #100;

        $finish;
    end
endmodule

simulasi_greenhouse.vcd
$date
	Mon Dec 01 17:36:05 2025
$end
$version
	Icarus Verilog
$end
$timescale
	1s
$end
$scope module tb_precision_greenhouse_fsm $end
$var wire 1 ! SS0_IDLE $end
$var wire 1 " SS7_CHAOS $end
$var wire 1 # SS6_GAS $end
$var wire 1 $ SS5_FLUSH $end
$var wire 1 % SS4_SPRAY $end
$var wire 1 & SS3_TEMP $end
$var wire 1 ' SS2_WATER $end
$var wire 1 ( SS1_NUTRI $end
$var wire 6 ) A_out [5:0] $end
$var parameter 32 * PERIOD $end
$var reg 6 + S_in [5:0] $end
$var reg 1 , clk $end
$var reg 1 - reset_n $end
$scope module DUT $end
$var wire 6 . S [5:0] $end
$var wire 1 ! SS0_IDLE $end
$var wire 1 " SS7_CHAOS $end
$var wire 1 , clk $end
$var wire 1 - reset_n $end
$var wire 1 # SS6_GAS $end
$var wire 1 $ SS5_FLUSH $end
$var wire 1 % SS4_SPRAY $end
$var wire 1 & SS3_TEMP $end
$var wire 1 ' SS2_WATER $end
$var wire 1 ( SS1_NUTRI $end
$var parameter 3 / ST_CHAOS $end
$var parameter 3 0 ST_FLUSH $end
$var parameter 3 1 ST_GAS $end
$var parameter 3 2 ST_IDLE $end
$var parameter 3 3 ST_NUTRI $end
$var parameter 3 4 ST_SPRAY $end
$var parameter 3 5 ST_TEMP $end
$var parameter 3 6 ST_WATER $end
$var reg 6 7 A [5:0] $end
$var reg 3 8 current_state [2:0] $end
$var reg 3 9 next_state [2:0] $end
$upscope $end
$upscope $end
$enddefinitions $end
$comment Show the parameter values. $end
$dumpall
b10 6
b11 5
b100 4
b1 3
b0 2
b110 1
b101 0
b111 /
b10100 *
$end
#0
$dumpvars
b0 9
b0 8
b0 7
b0 .
0-
0,
b0 +
b0 )
0(
0'
0&
0%
0$
0#
0"
0!
$end
#10
1,
#20
0,
#30
1,
#40
0,
1-
#50
1,
#60
0,
#70
1,
#80
b10 9
1'
0,
b10 +
b10 .
#90
b10 )
b10 7
b10 8
1,
#100
0,
#110
1,
#120
0,
#130
1,
#140
0,
#150
1,
#160
0,
#170
1,
#180
b11 9
1&
0,
b110 +
b110 .
#190
b100 )
b100 7
b11 8
1,
#200
0,
#210
1,
#220
0,
#230
1,
#240
0,
#250
1,
#260
0,
#270
1,
#280
0,
#290
1,
#300
b100 9
0'
1%
0,
b1100 +
b1100 .
#310
b1000 )
b1000 7
b100 8
1,
#320
0,
#330
1,
#340
0,
#350
1,
#360
0,
#370
1,
#380
0,
#390
1,
#400
b0 9
0&
0%
0,
b0 +
b0 .
#410
b0 )
b0 7
b0 8
1,
#420
0,
#430
1,
#440
b1 9
1(
0,
b1 +
b1 .
#450
b1 )
b1 7
b1 8
1,
#460
0,
#470
1,
#480
0,
#490
1,
#500
0,
#510
1,
#520
b101 9
0(
1$
0,
b10000 +
b10000 .
#530
b10000 )
b10000 7
b101 8
1,
#540
0,
#550
1,
#560
0,
#570
1,
#580
0,
#590
1,
#600
0,
#610
1,
#620
b10 9
1'
0$
0,
b10 +
b10 .
#630
b10 )
b10 7
b10 8
1,
#640
0,
#650
1,
#660
0,
#670
1,
#680
0,
#690
1,
#700
0,
#710
1,
#720
0,
#730
1,
#740
1(
0,
b11 +
b11 .
#750
1,
#760
0,
#770
1,
#780
0,
#790
1,
#800
0,
#810
1,
#820
0,
#830
1,
#840
0,
#850
1,
#860
0,
#870
1,
#880
0,
#890
b0 )
b0 7
b0 8
b0 9
0(
0'
1,
b0 +
b0 .
#900
0,
#910
1,
#920
0,
#930
b100000 )
b100000 7
b110 8
b110 9
1#
1,
b100000 +
b100000 .
#940
0,
#950
1,
#960
0,
#970
1,
#980
0,
#990
1,
#1000
0,
#1010
1,
#1020
0,
#1030
1,
#1040
0,
#1050
1,
#1060
0,
#1070
1,
#1080
0,
#1090
1,
#1100
0,
#1110
1,
#1120
0,
#1130
b0 )
b0 7
b0 8
b11 9
1&
0#
1,
b100 +
b100 .
#1140
0,
#1150
b100 )
b100 7
b11 8
1,
#1160
0,
#1170
1,
#1180
0,
#1190
1,
#1200
0,
#1210
1,
#1220
0,
#1230
b1 )
b1 7
b1 8
b1 9
1(
0&
1,
b1 +
b1 .
#1240
0,
#1250
1,
#1260
0,
#1270
1,
#1280
0,
#1290
1,
#1300
0,
#1310
b0 )
b0 7
b0 8
b0 9
0(
1,
b0 +
b0 .
